<?xml version="1.0" encoding="utf-8"?>
<Defs>
  <ThingDef Name="BaseWeapon_CP" Abstract="True" ParentName="BaseWeapon">
    <techLevel>Industrial</techLevel>
    <smeltable>true</smeltable>
    <burnableByRecipe>true</burnableByRecipe>
    <thingCategories>
      <li>WeaponsMelee</li>
      <li>CPWeapons</li>
    </thingCategories>
    <weaponClasses>
      <li>Melee</li>
    </weaponClasses>
    <relicChance>1</relicChance>
    <inspectorTabs>
      <li>ITab_Art</li>
    </inspectorTabs>
  </ThingDef>
  <ThingDef Name="BaseMeleeWeapon_CP" Abstract="True" ParentName="BaseMeleeWeapon">
    <thingCategories>
      <li>CPWeapons</li>
    </thingCategories>
  </ThingDef>
  <ThingDef Name="BaseMeleeWeapon_Sharp_CP" ParentName="BaseMeleeWeapon_Sharp" Abstract="True">
    <thingCategories>
      <li>CPWeapons</li>
    </thingCategories>
  </ThingDef>
  <ThingDef Name="BaseMeleeWeapon_Sharp_Quality_CP" ParentName="BaseMeleeWeapon_Sharp_Quality" Abstract="True">
    <thingCategories>
      <li>CPWeapons</li>
    </thingCategories>
  </ThingDef>
  <ThingDef ParentName="BaseMeleeWeapon_CP">
    <defName>MeleeWeapon_AKnife_CP</defName>
    <label>Arasaka combat knife</label>
    <description>A simple, yet very sturdy combat knife.  Well balanced and made from a special iron heavy alloy that allows it to retain an edge even after serious abuse.</description>
    <graphicData>
      <texPath>Things/Item/Equipment/WeaponMelee/Knife</texPath>
      <graphicClass>Graphic_Single</graphicClass>
    </graphicData>
    <costStuffCount>40</costStuffCount>
    <statBases>
      <MarketValue>150</MarketValue>
      <Mass>0.5</Mass>
    </statBases>
    <weaponTags>
      <li>Arasaka</li>
      <li>ArasakaMelee</li>
    </weaponTags>
    <equippedAngleOffset>-65</equippedAngleOffset>
    <tools>
      <li>
        <label>handle</label>
        <capacities>
          <li>Blunt</li>
        </capacities>
        <power>6</power>
        <cooldownTime>1.6</cooldownTime>
      </li>
      <li>
        <label>blade</label>
        <capacities>
          <li>Cut</li>
        </capacities>
        <power>10</power>
        <cooldownTime>1.5</cooldownTime>
      </li>
      <li>
        <label>point</label>
        <capacities>
          <li>Stab</li>
        </capacities>
        <power>10</power>
        <cooldownTime>1.5</cooldownTime>
      </li>
    </tools>
  </ThingDef>
  <ThingDef ParentName="BaseMeleeWeapon_CP">
    <defName>MeleeWeapon_IMIChainknife_CP</defName>
    <label>IMI Chainknife</label>
    <description>The IMI Chainknife is a miniature battery powered chainsaw; shaped somewhat like a survival knife with a 2 hour charge. It has seen a great deal of use by espionage agents.</description>
    <graphicData>
      <texPath>CP/Weapon/Chainknife</texPath>
      <graphicClass>Graphic_Single</graphicClass>
    </graphicData>
    <costStuffCount>40</costStuffCount>
    <statBases>
      <MarketValue>120</MarketValue>
      <Mass>0.5</Mass>
    </statBases>
    <equippedAngleOffset>-65</equippedAngleOffset>
    <tools>
      <li>
        <label>handle</label>
        <capacities>
          <li>Blunt</li>
        </capacities>
        <power>6</power>
        <cooldownTime>1.6</cooldownTime>
      </li>
      <li>
        <label>blade</label>
        <capacities>
          <li>Cut</li>
        </capacities>
        <power>9</power>
        <cooldownTime>1.56</cooldownTime>
      </li>
    </tools>
    <equippedStatOffsets>
      <PlantWorkSpeed>0.1</PlantWorkSpeed>
    </equippedStatOffsets>
  </ThingDef>
  <ThingDef ParentName="BaseMeleeWeapon_CP">
    <defName>MeleeWeapon_Monoknife_CP</defName>
    <label>Kendachi Monoknife</label>
    <description>The Kendachi Monoknife® is a melee weapon An incredibly sharp, mono-sectional crystal blade. Produced in the Japanese "tanto" style.</description>
    <graphicData>
      <texPath>Things/Item/Equipment/WeaponMelee/Knife</texPath>
      <graphicClass>Graphic_Single</graphicClass>
      <color>(83,213,253)</color>
    </graphicData>
    <costStuffCount>40</costStuffCount>
    <statBases>
      <MarketValue>200</MarketValue>
      <Mass>0.5</Mass>
    </statBases>
    <equippedAngleOffset>-65</equippedAngleOffset>
    <tools>
      <li>
        <label>handle</label>
        <capacities>
          <li>Blunt</li>
        </capacities>
        <power>6</power>
        <cooldownTime>1.6</cooldownTime>
      </li>
      <li>
        <label>blade</label>
        <capacities>
          <li>Cut</li>
        </capacities>
        <power>12</power>
        <cooldownTime>1.5</cooldownTime>
      </li>
      <li>
        <label>point</label>
        <capacities>
          <li>Stab</li>
        </capacities>
        <power>12</power>
        <cooldownTime>1.5</cooldownTime>
      </li>
    </tools>
  </ThingDef>
  <ThingDef ParentName="BaseMeleeWeapon_Sharp_Quality_CP">
    <defName>MeleeWeapon_Chainknife_CP</defName>
    <label>chainknife</label>
    <description>These chainknives are hand made, similar to the chainknife produced by IMI.</description>
    <graphicData>
      <texPath>CP/Weapon/Chainknife</texPath>
      <graphicClass>Graphic_Single</graphicClass>
    </graphicData>
    <statBases>
      <WorkToMake>8000</WorkToMake>
      <Mass>0.5</Mass>
    </statBases>
    <equippedAngleOffset>-65</equippedAngleOffset>
    <costStuffCount>40</costStuffCount>
    <stuffCategories>
      <li>Metallic</li>
    </stuffCategories>
    <costList>
      <ComponentIndustrial>8</ComponentIndustrial>
    </costList>
    <tools>
      <li>
        <label>handle</label>
        <capacities>
          <li>Blunt</li>
        </capacities>
        <power>6</power>
        <cooldownTime>1.6</cooldownTime>
      </li>
      <li>
        <label>blade</label>
        <capacities>
          <li>Cut</li>
        </capacities>
        <power>8</power>
        <cooldownTime>1.56</cooldownTime>
      </li>
    </tools>
    <equippedStatOffsets>
      <PlantWorkSpeed>0.1</PlantWorkSpeed>
    </equippedStatOffsets>
    <recipeMaker>
      <researchPrerequisite>Smithing</researchPrerequisite>
    </recipeMaker>
  </ThingDef>
  <ThingDef ParentName="BaseMeleeWeapon_CP">
    <defName>MeleeWeapon_PowerSword_CP</defName>
    <label>Kendachi Powersword</label>
    <description>Combining elements of the popular Kendachi monoline with a powered handle, the powersword vibrates its molecular crystal blade 2000 per minute. Combined with a microscopically serrated edge, this weapon literally chews its way through anything it encounteres.</description>
    <graphicData>
      <texPath>CP/Weapon/powersword</texPath>
      <graphicClass>Graphic_Single</graphicClass>
    </graphicData>
    <costStuffCount>120</costStuffCount>
    <statBases>
      <MarketValue>860</MarketValue>
      <Mass>3</Mass>
    </statBases>
    <equippedAngleOffset>-65</equippedAngleOffset>
    <tools>
      <li>
        <label>handle</label>
        <capacities>
          <li>Blunt</li>
        </capacities>
        <power>6</power>
        <cooldownTime>2.5</cooldownTime>
      </li>
      <li>
        <label>edge</label>
        <capacities>
          <li>Cut</li>
        </capacities>
        <power>18</power>
        <cooldownTime>2.5</cooldownTime>
      </li>
      <li>
        <label>point</label>
        <capacities>
          <li>Stab</li>
        </capacities>
        <power>27</power>
        <cooldownTime>2.5</cooldownTime>
      </li>
    </tools>
  </ThingDef>
  <ThingDef ParentName="BaseMeleeWeapon_Sharp_Quality_CP">
    <defName>MeleeWeapon_Katana_CP</defName>
    <label>katana</label>
    <techLevel>Medieval</techLevel>
    <description>Katanas were one of the traditionally made Japanese swords that were used by the samurai of ancient and feudal Japan. Today they are popular in asian communities by those who view themselves as rimworld ronin.</description>
    <graphicData>
      <texPath>CP/Weapon/katana</texPath>
      <graphicClass>Graphic_Single</graphicClass>
    </graphicData>
    <costStuffCount>120</costStuffCount>
    <statBases>
      <WorkToMake>25000</WorkToMake>
      <Mass>3</Mass>
    </statBases>
    <equippedAngleOffset>-65</equippedAngleOffset>
    <stuffCategories>
      <li>Metallic</li>
    </stuffCategories>
    <tools>
      <li>
        <label>handle</label>
        <capacities>
          <li>Blunt</li>
        </capacities>
        <power>6</power>
        <cooldownTime>2.5</cooldownTime>
      </li>
      <li>
        <label>blade</label>
        <capacities>
          <li>Cut</li>
        </capacities>
        <power>18</power>
        <cooldownTime>2.5</cooldownTime>
      </li>
      <li>
        <label>point</label>
        <capacities>
          <li>Stab</li>
        </capacities>
        <power>27</power>
        <cooldownTime>2.5</cooldownTime>
      </li>
    </tools>
    <recipeMaker>
      <researchPrerequisite>LongBlades</researchPrerequisite>
    </recipeMaker>
  </ThingDef>
  <ThingDef ParentName="BaseWeapon_CP">
    <defName>MeleeWeapon_AKatana_CP</defName>
    <label>Arasaka Katana</label>
    <description>Arasaka grows their swords in orbit, their crystalline matrices aligned to make a sword that is stronger and sharper than any terrestrial metal. These swords are not sold by Arasaka, but given to their soldiers as a symbol of honor when they are prometed to officers.</description>
    <graphicData>
      <texPath>CP/Weapon/katana</texPath>
      <graphicClass>Graphic_Single</graphicClass>
    </graphicData>
    <statBases>
      <MarketValue>300</MarketValue>
      <Mass>3</Mass>
    </statBases>
    <weaponTags>
      <li>Arasaka</li>
      <li>ArasakaMelee</li>
    </weaponTags>
    <equippedAngleOffset>-65</equippedAngleOffset>
    <tools>
      <li>
        <label>handle</label>
        <capacities>
          <li>Blunt</li>
        </capacities>
        <power>6</power>
        <cooldownTime>2.4</cooldownTime>
      </li>
      <li>
        <label>blade</label>
        <capacities>
          <li>Cut</li>
        </capacities>
        <power>18</power>
        <cooldownTime>2.4</cooldownTime>
      </li>
      <li>
        <label>point</label>
        <capacities>
          <li>Stab</li>
        </capacities>
        <power>27</power>
        <cooldownTime>2.4</cooldownTime>
      </li>
    </tools>
  </ThingDef>
  <ThingDef ParentName="BaseMeleeWeapon_CP">
    <defName>MeleeWeapon_MonoKatana_CP</defName>
    <label>Kendachi Monokatana</label>
    <description>The monokatana is an incredibally sharp. mono-molecular crystal blade in the style of a katana.</description>
    <graphicData>
      <texPath>CP/Weapon/katana</texPath>
      <graphicClass>Graphic_Single</graphicClass>
      <color>(83,213,253)</color>
    </graphicData>
    <costStuffCount>120</costStuffCount>
    <statBases>
      <MarketValue>600</MarketValue>
      <MaxHitPoints>50</MaxHitPoints>
      <Mass>2</Mass>
    </statBases>
    <equippedAngleOffset>-65</equippedAngleOffset>
    <tools>
      <li>
        <label>handle</label>
        <capacities>
          <li>Blunt</li>
        </capacities>
        <power>6</power>
        <cooldownTime>1.6</cooldownTime>
      </li>
      <li>
        <label>blade</label>
        <capacities>
          <li>Cut</li>
        </capacities>
        <power>24</power>
        <cooldownTime>2.5</cooldownTime>
      </li>
      <li>
        <label>point</label>
        <capacities>
          <li>Stab</li>
        </capacities>
        <power>36</power>
        <cooldownTime>2.5</cooldownTime>
      </li>
    </tools>
  </ThingDef>
  <ThingDef ParentName="BaseMeleeWeapon_CP">
    <defName>MeleeWeapon_MonoKatana2_CP</defName>
    <label>Kendachi Mono-Two</label>
    <description>An improved version of the original Kendachi Monoblade, favored by corporate samurai everywhere. A thicker blade cross section reinforced with Orbital crystal strengthens the weapon against parries.</description>
    <graphicData>
      <texPath>CP/Weapon/katana</texPath>
      <graphicClass>Graphic_Single</graphicClass>
      <color>(83,213,253)</color>
    </graphicData>
    <costStuffCount>120</costStuffCount>
    <statBases>
      <MarketValue>700</MarketValue>
      <MaxHitPoints>100</MaxHitPoints>
      <Mass>2</Mass>
    </statBases>
    <equippedAngleOffset>-65</equippedAngleOffset>
    <tools>
      <li>
        <label>handle</label>
        <capacities>
          <li>Blunt</li>
        </capacities>
        <power>6</power>
        <cooldownTime>1.6</cooldownTime>
      </li>
      <li>
        <label>blade</label>
        <capacities>
          <li>Cut</li>
        </capacities>
        <power>24</power>
        <cooldownTime>2.4</cooldownTime>
      </li>
      <li>
        <label>point</label>
        <capacities>
          <li>Stab</li>
        </capacities>
        <power>36</power>
        <cooldownTime>2.4</cooldownTime>
      </li>
    </tools>
  </ThingDef>
  <ThingDef ParentName="BaseWeapon_CP">
    <defName>MeleeWeapon_IMIChainsword_CP</defName>
    <label>IMI Chainsword</label>
    <description>Since their chain knife sold so well, IMI decided to up the stakes and released a full scale sword.  The balance is a bit off, but this weapons will simply tear through just about anything that stands in its way.  It comes with a custom sheath.</description>
    <graphicData>
      <texPath>CP/Weapon/Chainsword</texPath>
      <graphicClass>Graphic_Single</graphicClass>
    </graphicData>
    <statBases>
      <MarketValue>540</MarketValue>
      <Mass>3</Mass>
    </statBases>
    <equippedAngleOffset>-65</equippedAngleOffset>
    <tools>
      <li>
        <label>handle</label>
        <capacities>
          <li>Blunt</li>
        </capacities>
        <power>6</power>
        <cooldownTime>2.8</cooldownTime>
      </li>
      <li>
        <label>blade</label>
        <capacities>
          <li>Cut</li>
        </capacities>
        <power>24</power>
        <cooldownTime>2.8</cooldownTime>
      </li>
    </tools>
    <equippedStatOffsets>
      <PlantWorkSpeed>0.2</PlantWorkSpeed>
    </equippedStatOffsets>
  </ThingDef>
  <ThingDef ParentName="BaseMeleeWeapon_Sharp_CP">
    <defName>MeleeWeapon_Chainsword_CP</defName>
    <label>Chainsword</label>
    <techLevel>Industrial</techLevel>
    <description>These swords have begun to appear at the hands of pirates and raiders. They are all handmade; powered either by combustion engine or electric.</description>
    <graphicData>
      <texPath>CP/Weapon/Chainsword</texPath>
      <graphicClass>Graphic_Single</graphicClass>
    </graphicData>
    <statBases>
      <WorkToMake>35000</WorkToMake>
      <MarketValue>500</MarketValue>
      <Mass>3</Mass>
    </statBases>
    <costStuffCount>80</costStuffCount>
    <stuffCategories>
      <li>Metallic</li>
    </stuffCategories>
    <costList>
      <ComponentIndustrial>8</ComponentIndustrial>
    </costList>
    <weaponTags>
      <li>NeolithicMelee</li>
    </weaponTags>
    <equippedAngleOffset>-65</equippedAngleOffset>
    <tools>
      <li>
        <label>handle</label>
        <capacities>
          <li>Blunt</li>
        </capacities>
        <power>6</power>
        <cooldownTime>3</cooldownTime>
      </li>
      <li>
        <label>blade</label>
        <capacities>
          <li>Cut</li>
        </capacities>
        <power>27</power>
        <cooldownTime>3</cooldownTime>
      </li>
    </tools>
    <equippedStatOffsets>
      <PlantWorkSpeed>0.2</PlantWorkSpeed>
    </equippedStatOffsets>
    <recipeMaker>
      <researchPrerequisite>LongBlades</researchPrerequisite>
    </recipeMaker>
  </ThingDef>
  <ThingDef ParentName="BaseWeapon_CP">
    <defName>MeleeWeapon_Battleglove_CP</defName>
    <label>Gibson Battlegear SPM-1 Battleglove</label>
    <description>This is a large gauntlet covering the hand and forearm, increasing the power of the user's punches.</description>
    <graphicData>
      <texPath>CP/Weapon/Battleglove</texPath>
      <graphicClass>Graphic_Single</graphicClass>
    </graphicData>
    <statBases>
      <MarketValue>500</MarketValue>
      <Mass>3</Mass>
    </statBases>
    <equippedAngleOffset>-90</equippedAngleOffset>
    <tools>
      <li>
        <label>fist</label>
        <capacities>
          <li>Blunt</li>
        </capacities>
        <power>12</power>
        <cooldownTime>3</cooldownTime>
      </li>
    </tools>
    <equippedStatOffsets>
      <PlantWorkSpeed>0.2</PlantWorkSpeed>
    </equippedStatOffsets>
  </ThingDef>
</Defs>